MANIFEST.in
setup.py
fcdjangoutils/__app__.py
fcdjangoutils/__init__.py
fcdjangoutils/context_processors.py
fcdjangoutils/cookieview.py
fcdjangoutils/cors.py
fcdjangoutils/date.py
fcdjangoutils/db.py
fcdjangoutils/extendable_permissions.py
fcdjangoutils/fields.py
fcdjangoutils/geomodels.py
fcdjangoutils/jsonview.py
fcdjangoutils/mail.py
fcdjangoutils/middleware.py
fcdjangoutils/modelhelpers.py
fcdjangoutils/models.py
fcdjangoutils/monkeypatching.py
fcdjangoutils/querytree.py
fcdjangoutils/responseutils.py
fcdjangoutils/signalautoconnectmodel.py
fcdjangoutils/sqlutils.py
fcdjangoutils/templatetaghelpers.py
fcdjangoutils/tests.py
fcdjangoutils/timer.py
fcdjangoutils/urlresolver.py
fcdjangoutils/views.py
fcdjangoutils/widgettagmiddleware.py
fcdjangoutils.egg-info/PKG-INFO
fcdjangoutils.egg-info/SOURCES.txt
fcdjangoutils.egg-info/dependency_links.txt
fcdjangoutils.egg-info/top_level.txt
fcdjangoutils/locale/no/LC_MESSAGES/django.po
fcdjangoutils/locale/no/LC_MESSAGES/djangojs.po
fcdjangoutils/management/__init__.py
fcdjangoutils/management/commands/__init__.py
fcdjangoutils/management/commands/exportdbconfig.py
fcdjangoutils/management/commands/makemessagesworkaround.py
fcdjangoutils/media/fcdjangoutils/css/expand.css
fcdjangoutils/media/fcdjangoutils/js/expand.js
fcdjangoutils/media/fcdjangoutils/js/fcdjangoutils.js
fcdjangoutils/media/fcdjangoutils/js/jquery-1.4.4.min.js
fcdjangoutils/media/fcdjangoutils/js/jquery-ui-1.8.6.custom.min.js
fcdjangoutils/media/fcdjangoutils/js/jquery-ui.js
fcdjangoutils/media/fcdjangoutils/js/jquery.js
fcdjangoutils/media/fcdjangoutils/js/jquery.ui.datepicker-no.js
fcdjangoutils/media/fcdjangoutils/js/jquery.ui.selectmenu.js
fcdjangoutils/media/fcdjangoutils/js/obj.js
fcdjangoutils/media/fcdjangoutils/js/underscore.js
fcdjangoutils/media/fcdjangoutils/js/jquery-validate/additional-methods.js
fcdjangoutils/media/fcdjangoutils/js/jquery-validate/changelog.txt
fcdjangoutils/media/fcdjangoutils/js/jquery-validate/jquery.validate.js
fcdjangoutils/media/fcdjangoutils/js/jquery-validate/jquery.validate.min.js
fcdjangoutils/media/fcdjangoutils/js/jquery-validate/jquery.validate.pack.js
