Metadata-Version: 1.0
Name: fcdjangoutils
Version: 0.0.2
Summary: A collection of various small Django utilities.
Home-page: http://github.com/redhog/fcdjangoutils
Author: RedHog (Egil Moeller)
Author-email: egil.moller@piratpartiet.se
License: GPL
Keywords: django utils
Platform: UNKNOWN
